skipcash/__init__.py
skipcash/api_operations/__init__.py
skipcash/api_operations/create.py
skipcash/api_operations/retrieve.py
skipcash/api_resources/__init__.py
skipcash/api_resources/payment.py
skipcash/api_resources/webhook.py
skipcash/client/__init__.py
skipcash/client/api_client.py
skipcash/exceptions/__init__.py
skipcash/exceptions/api_error.py
skipcash/responses/__init__.py
skipcash/responses/payment_response.py
skipcash/responses/response_handler.py
skipcash/schema/__init__.py
skipcash/schema/payment_schema.py
skipcash/schema/webhook_schema.py
skipcash/utils/__init__.py
skipcash/utils/decorators.py
skipcash/utils/helper.py
skipcash/utils/http_client.py
skipcash/utils/signature.py
tests/__init__.py
tests/create_payment.py
tests/get_payment.py
tests/webhook.py
skipcash-0.0.4.dist-info/LICENSE
skipcash-0.0.4.dist-info/METADATA
skipcash-0.0.4.dist-info/WHEEL
skipcash-0.0.4.dist-info/top_level.txt
skipcash-0.0.4.dist-info/RECORD
