Metadata-Version: 2.1
Name: skipcash
Version: 0.0.4
Summary: The SkipCash SDK for Python enables developers to easily integrate SkipCash payment services into their Python applications.
Home-page: https://codelounge.io
Author: Muhammad Arshad
Author-email: arshad@codelounge.io
Keywords: SkipCash Python SDK,skipcash,skipcash-sdk,skipcash-python
Classifier: Development Status :: 3 - Alpha
Classifier: Intended Audience :: Developers
Classifier: License :: OSI Approved :: MIT License
Classifier: Programming Language :: Python :: 3.10
License-File: LICENSE
Requires-Dist: annotated-types
Requires-Dist: certifi
Requires-Dist: charset-normalizer
Requires-Dist: idna
Requires-Dist: pip
Requires-Dist: pycountry
Requires-Dist: requests
Requires-Dist: setuptools
Requires-Dist: urllib3
Requires-Dist: wheel
